awswrapper/__init__.py
awswrapper/ec2wrapper.py
awswrapper-0.3.0.dist-info/DESCRIPTION.rst
awswrapper-0.3.0.dist-info/METADATA
awswrapper-0.3.0.dist-info/RECORD
awswrapper-0.3.0.dist-info/WHEEL
awswrapper-0.3.0.dist-info/metadata.json
awswrapper-0.3.0.dist-info/top_level.txt
