Metadata-Version: 2.0
Name: awswrapper
Version: 0.3.0
Summary: Wrapper of AWS API to use with Lambda
Home-page: https://github.com/EclecticIQ/python-aws-wrapper
Author: Hector Reyes Aleman
Author-email: hector@eclecticiq.com
License: BSD
Platform: UNKNOWN
Requires-Dist: boto3
